linode/__init__.py
linode/common.py
linode/errors.py
linode/linode_client.py
linode/login_client.py
linode/paginated_list.py
linode/objects/__init__.py
linode/objects/base.py
linode/objects/dbase.py
linode/objects/filtering.py
linode/objects/image.py
linode/objects/region.py
linode/objects/volume.py
linode/objects/account/__init__.py
linode/objects/account/account.py
linode/objects/account/event.py
linode/objects/account/invoice.py
linode/objects/account/invoiceitem.py
linode/objects/account/oauth_client.py
linode/objects/account/payment.py
linode/objects/account/settings.py
linode/objects/account/user.py
linode/objects/account/user_grant.py
linode/objects/domain/__init__.py
linode/objects/domain/domain.py
linode/objects/domain/record.py
linode/objects/linode/__init__.py
linode/objects/linode/backup.py
linode/objects/linode/config.py
linode/objects/linode/disk.py
linode/objects/linode/kernel.py
linode/objects/linode/linode.py
linode/objects/linode/linode_type.py
linode/objects/linode/stackscript.py
linode/objects/longview/__init__.py
linode/objects/longview/client.py
linode/objects/longview/subscription.py
linode/objects/networking/__init__.py
linode/objects/networking/ip6address.py
linode/objects/networking/ip6pool.py
linode/objects/networking/ip6range.py
linode/objects/networking/ipaddress.py
linode/objects/nodebalancer/__init__.py
linode/objects/nodebalancer/config.py
linode/objects/nodebalancer/node.py
linode/objects/nodebalancer/nodebalancer.py
linode/objects/profile/__init__.py
linode/objects/profile/app.py
linode/objects/profile/personal_access_token.py
linode/objects/profile/profile.py
linode/objects/profile/whitelist_entry.py
linode/objects/support/__init__.py
linode/objects/support/reply.py
linode/objects/support/ticket.py
linode_api-4.1.9b1.dist-info/DESCRIPTION.rst
linode_api-4.1.9b1.dist-info/METADATA
linode_api-4.1.9b1.dist-info/RECORD
linode_api-4.1.9b1.dist-info/WHEEL
linode_api-4.1.9b1.dist-info/metadata.json
linode_api-4.1.9b1.dist-info/top_level.txt
test/__init__.py
test/base.py
test/fixtures.py
test/linode_client_test.py
test/paginated_list_test.py
test/objects/__init__.py
test/objects/image_tests.py
