Metadata-Version: 2.0
Name: linode-api
Version: 4.1.9b1
Summary: The official python SDK for Linode API v4
Home-page: https://github.com/linode/python-linode-api
Author: Linode
Author-email: developers@linode.com
License: BSD 3-Clause License
Keywords: linode cloud hosting infrastructure
Platform: UNKNOWN
Classifier: Development Status :: 4 - Beta
Classifier: Intended Audience :: Developers
Classifier: Topic :: Software Development :: Libraries
Classifier: License :: OSI Approved :: BSD License
Classifier: Programming Language :: Python
Classifier: Programming Language :: Python :: 2
Classifier: Programming Language :: Python :: 2.7
Classifier: Programming Language :: Python :: 3
Classifier: Programming Language :: Python :: 3.2
Classifier: Programming Language :: Python :: 3.3
Classifier: Programming Language :: Python :: 3.4
Classifier: Programming Language :: Python :: 3.5
Requires-Dist: future
Requires-Dist: requests
